aworda/lbot/__init__.py
aworda/lbot/config.py
aworda/lbot/database.py
aworda/lbot/dispatcher.py
aworda/lbot/permission.py
aworda/lbot/utils.py
aworda_lbot-0.0.1.dist-info/LICENSE
aworda_lbot-0.0.1.dist-info/WHEEL
aworda_lbot-0.0.1.dist-info/METADATA
aworda_lbot-0.0.1.dist-info/RECORD
